Workbook

Sheet Mode emploi
A1: Repère | B1: Instruction
A2: Statut | B2: Projet personnel de conception · Événement en préparation
A3: Période publique | B3: Avril 2027 ; date exacte à confirmer
A4: Date de travail | B4: 08/04/2027 = référence non confirmée, à modifier après validation
A5: Cellules bleues | B5: Données ou hypothèses modifiables
A6: Formules | B6: Calcul automatique à l’ouverture dans un tableur compatible
A7: Données inconnues | B7: Ne pas remplacer les cellules de résultats vides par des résultats fictifs
A8: Budget | B8: Tous les montants sont des hypothèses TTC à confirmer par devis
A9: Rétroplanning | B9: Dates calculées depuis la cellule B2 de la feuille Paramètres
A10: Données personnelles | B10: Ce modèle ne contient aucune liste de participants
A11: Version | B11: V1.0 · 13 octobre 2026 · Farès Benamar

Sheet Paramètres
A1: Paramètre | B1: Valeur
A2: Date de référence | B2: 46485
A3: Participants visés | B3: 80
A4: Capacité minimale salle | B4: 100
A5: Équipe maximale | B5: 8
A6: Statut | B6: Date de référence non confirmée ; diffusion publique : avril 2027

Sheet Budget
A1: Poste | B1: Quantité | C1: Prix unitaire TTC | D1: Total TTC | E1: Hypothèse / validation
A2: Location de salle | B2: 1 | C2: 600 | D2: =B2*C2 | E2: Hypothèse ; capacité 100 personnes et accessibilité à confirmer
A3: Sonorisation et régie | B3: 1 | C3: 450 | D3: =B3*C3 | E3: Deux micros, diffusion sonore, technicien selon devis
A4: Interventions et modération | B4: 1 | C4: 300 | D4: =B4*C4 | E4: Enveloppe globale indicative ; conditions à convenir
A5: Collation légère | B5: ='Paramètres'!B3 | C5: 3 | D5: =B5*C5 | E5: Hypothèse par participant ; eau et boissons sans alcool
A6: Impression et signalétique | B6: 1 | C6: 90 | D6: =B6*C6 | E6: Affiches, programme et repères d’accueil
A7: Assurance et frais administratifs | B7: 1 | C7: 120 | D7: =B7*C7 | E7: Hypothèse à préciser avec la structure porteuse
A8: Accessibilité et adaptations | B8: 1 | C8: 120 | D8: =B8*C8 | E8: Provision ; besoins à recueillir avant l’événement
A9: Photographie / documentation | B9: 1 | C9: 180 | D9: =B9*C9 | E9: Option selon devis et consentement des personnes
A10: Sous-total | D10: =SUM(D2:D9) | E10: Hypothèses, pas des dépenses engagées
A11: Réserve | B11: 0.1 | D11: =ROUND(D10*B11,2) | E11: Taux modifiable
A12: Total prévisionnel | D12: =D10+D11 | E12: Montants TTC à confirmer
A13: Plafond de travail | D13: 2500 | E13: À valider avant engagement
A14: Marge disponible | D14: =D13-D12 | E14: Peut devenir négative après modification des hypothèses
A15: Contribution envisagée | D15: 1500 | E15: Scénario non validé ; aucun financement acquis
A16: Solde à financer | D16: =MAX(0,D12-D15) | E16: À couvrir ou arbitrer, sans partenaire confirmé

Sheet Rétroplanning
A1: Début relatif | B1: Fin relative | C1: Phase | D1: Action | E1: Pilote proposé | F1: Livrable | G1: Statut | H1: Début calculé | I1: Fin calculée
A2: -56 | B2: -49 | C2: Cadrage | D2: Valider le concept, le public et l’enveloppe | E2: Responsable projet | F2: Dossier de conception | G2: À valider | H2: ='Paramètres'!$B$2+A2 | I2: ='Paramètres'!$B$2+B2
A3: -49 | B3: -42 | C3: Lieu | D3: Comparer les lieux, les accès et les devis | E3: Logistique | F3: Fiche lieu et devis | G3: À lancer | H3: ='Paramètres'!$B$2+A3 | I3: ='Paramètres'!$B$2+B3
A4: -42 | B4: -35 | C4: Programme | D4: Identifier puis confirmer les deux intervenants et la modération | E4: Éditorial | F4: Accords écrits et biographies | G4: À lancer | H4: ='Paramètres'!$B$2+A4 | I4: ='Paramètres'!$B$2+B4
A5: -42 | B5: -28 | C5: Technique | D5: Confirmer salle, assurance, besoins audio et accessibilité | E5: Logistique / régie | F5: Fiche technique | G5: À lancer | H5: ='Paramètres'!$B$2+A5 | I5: ='Paramètres'!$B$2+B5
A6: -35 | B6: -28 | C6: Supports | D6: Adapter affiche, invitation et page aux informations confirmées | E6: Communication | F6: Supports validés | G6: À préparer | H6: ='Paramètres'!$B$2+A6 | I6: ='Paramètres'!$B$2+B6
A7: -28 | B7: -21 | C7: Inscriptions | D7: Ouvrir le formulaire et annoncer le rendez-vous | E7: Communication / accueil | F7: Page et formulaire validés | G7: Non ouvert | H7: ='Paramètres'!$B$2+A7 | I7: ='Paramètres'!$B$2+B7
A8: -21 | B8: -14 | C8: Relais | D8: Diffuser les messages et solliciter les relais pertinents | E8: Communication | F8: Suivi des canaux | G8: À préparer | H8: ='Paramètres'!$B$2+A8 | I8: ='Paramètres'!$B$2+B8
A9: -14 | B9: -7 | C9: Conduite | D9: Brief des intervenants et validation du déroulé | E9: Responsable projet | F9: Conducteur partagé | G9: À préparer | H9: ='Paramètres'!$B$2+A9 | I9: ='Paramètres'!$B$2+B9
A10: -7 | B10: -2 | C10: Accueil | D10: Vérifier les inscrits, les besoins et les confirmations | E10: Accueil | F10: Liste d’accueil à accès limité | G10: À préparer | H10: ='Paramètres'!$B$2+A10 | I10: ='Paramètres'!$B$2+B10
A11: -2 | B11: -1 | C11: Répétition | D11: Tester matériel et consignes avec l’équipe | E11: Régie / logistique | F11: Check-list technique | G11: À préparer | H11: ='Paramètres'!$B$2+A11 | I11: ='Paramètres'!$B$2+B11
A12: 0 | B12: 0 | C12: Événement | D12: Déployer le conducteur, accueillir et documenter | E12: Équipe complète | F12: Journal des écarts | G12: Non réalisé | H12: ='Paramètres'!$B$2+A12 | I12: ='Paramètres'!$B$2+B12
A13: 1 | B13: 3 | C13: Retour | D13: Envoyer remerciement, questionnaire et ressources | E13: Communication | F13: Message et questionnaire | G13: À préparer | H13: ='Paramètres'!$B$2+A13 | I13: ='Paramètres'!$B$2+B13
A14: 3 | B14: 7 | C14: Bilan | D14: Rapprocher dépenses, fréquentation et retours | E14: Responsable projet | F14: Bilan factuel et suites | G14: Non mesuré | H14: ='Paramètres'!$B$2+A14 | I14: ='Paramètres'!$B$2+B14

Sheet Déroulé
A1: Début | B1: Fin | C1: Séquence | D1: Pilote proposé | E1: Préparation | F1: Vigilance
A2: 16:00 | B2: 16:45 | C2: Installation | D2: Logistique / régie | E2: Salle, flux, sonorisation, signalétique | F2: Vérifier accès, issues et capacité avec le lieu
A3: 16:45 | B3: 17:15 | C3: Tests techniques | D3: Régie | E3: Micros, niveaux, présentation | F3: Tester le plan de secours sans projection
A4: 17:15 | B4: 17:45 | C4: Brief équipe | D4: Responsable projet | E4: Rôles, accueil, incidents, consentement | F4: Rappeler les responsables du lieu et les contacts
A5: 17:45 | B5: 18:15 | C5: Brief intervenants | D5: Éditorial / modération | E5: Fil conducteur et timing | F5: Confirmer les noms seulement après accord
A6: 18:15 | B6: 18:30 | C6: Mise en place accueil | D6: Accueil | E6: Liste, badges et supports | F6: Installer une file accessible et éviter l’affichage des coordonnées
A7: 18:30 | B7: 19:00 | C7: Accueil du public | D7: Accueil / logistique | E7: Orientation et installation | F7: Noter le nombre d’entrées, sans double comptage
A8: 19:00 | B8: 19:10 | C8: Ouverture | D8: Responsable projet / modération | E8: Intention et règles d’échange | F8: Présenter les intervenants confirmés
A9: 19:10 | B9: 19:45 | C9: Table ronde | D9: Modération + deux intervenants | E9: Réseaux sociaux, sources et IA | F9: Limiter les prises de parole et distinguer faits et opinions
A10: 19:45 | B10: 20:10 | C10: Questions du public | D10: Modération | E10: Questions regroupées par thème | F10: Faire circuler le micro de façon inclusive
A11: 20:10 | B11: 20:25 | C11: Pause | D11: Logistique | E11: Collation et échanges | F11: Réduire déchets et congestion
A12: 20:25 | B12: 20:55 | C12: Atelier collectif | D12: Modération / éditorial | E12: Examiner une information et ses sources | F12: Utiliser un exemple documenté, sans exposer de données personnelles
... A15: 21:30 | B15: 21:45 | C15: Sortie et remise en état | D15: Logistique / régie | E15: Rangement et restitution | F15: Vérifier salle, matériel et objets trouvés

Sheet RACI
A1: Action | B1: Responsable projet | C1: Éditorial | D1: Communication | E1: Logistique | F1: Accueil
A2: Concept et budget | B2: A/R | C2: C | D2: C | E2: C | F2: I
A3: Programme et intervenants | B3: A | C3: R | D3: C | E3: I | F3: I
A4: Lieu et technique | B4: A | C4: C | D4: I | E4: R | F4: C
A5: Supports et diffusion | B5: A | C5: C | D5: R | E5: C | F5: I
A6: Inscriptions et accueil | B6: A | C6: I | D6: C | E6: C | F6: R
A7: Déroulé et brief équipe | B7: A/R | C7: C | D7: C | E7: C | F7: C
A8: Bilan et suivi | B8: A | C8: C | D8: R | E8: C | F8: C

Sheet Risques
A1: Risque | B1: Probabilité | C1: Impact | D1: Prévention / repli | E1: Pilote | F1: Statut
A2: Lieu ou financement non confirmé | B2: Fort | C2: Fort | D2: Ne pas ouvrir les inscriptions avant décision écrite ; comparer au moins deux options | E2: Responsable projet | F2: Non vérifié
A3: Désistement d’un intervenant | B3: Moyen | C3: Fort | D3: Confirmer par écrit ; prévoir un format à un intervenant et une séquence de questions étendue | E3: Éditorial | F3: À préparer
A4: Inscrits absents | B4: Moyen | C4: Moyen | D4: Rappel à J-2, confirmation simple et liste d’attente sans dépasser la jauge | E4: Accueil | F4: À préparer
A5: Panne audio / projection | B5: Moyen | C5: Fort | D5: Test J-1 et le jour même ; conducteur et supports imprimés de secours | E5: Régie | F5: À tester
A6: Besoin d’accessibilité non anticipé | B6: Moyen | C6: Fort | D6: Vérifier le lieu et offrir un contact pour recueillir les besoins, sans demander de diagnostic médical | E6: Logistique | F6: À vérifier
A7: Photo ou donnée utilisée sans accord | B7: Moyen | C7: Fort | D7: Informer, recueillir l’accord pour les usages prévus et limiter les accès à la liste d’inscrits | E7: Communication | F7: À préparer
A8: Incident dans le lieu | B8: Faible | C8: Fort | D8: Suivre le protocole du lieu ; repérer issues, personnel référent et moyens d’alerte | E8: Logistique | F8: À confirmer avec le lieu
A9: Dérive budgétaire | B9: Moyen | C9: Fort | D9: Aucun engagement sans validation ; réserve de 10 % et arbitrage des options avant commande | E9: Responsable projet | F9: À suivre

Sheet Diffusion
A1: Échéance | B1: Canal | C1: Contenu | D1: Objectif | E1: Statut
A2: -28 | B2: Page et e-mail | C2: Programme validé, informations pratiques et inscription | D2: Ouverture après validation | E2: À préparer
A3: -21 | B3: Réseaux et relais | C3: Angle éditorial et invitation | D3: Faire connaître le rendez-vous | E3: À préparer
A4: -14 | B4: Réseaux | C4: Programme et présentation des intervenants confirmés | D4: Préciser la valeur de la soirée | E4: À préparer
A5: -7 | B5: Page et e-mail | C5: Accès, horaires et conditions | D5: Préparer la venue | E5: À préparer
A6: -2 | B6: E-mail inscrits | C6: Rappel et désistement | D6: Confirmer / libérer les places | E6: À préparer
A7: 1 | B7: E-mail participants | C7: Remerciement et ressources | D7: Prolonger les échanges | E7: À préparer
A8: 7 | B8: Bilan interne | C8: Données vérifiées et améliorations | D8: Décider des suites | E8: Non mesuré

Sheet Indicateurs
A1: Indicateur | B1: Valeur | C1: Statut / définition
A2: Participants visés | B2: ='Paramètres'!B3 | C2: Objectif, pas un résultat
A3: Inscriptions confirmées | C3: À renseigner après ouverture
A4: Entrées uniques | C4: À renseigner après l’événement
A5: Taux de présence | B5: =IF(COUNT(B3:B4)<2,"",IFERROR(B4/B3,"")) | C5: Entrées uniques / inscriptions confirmées
A6: Questionnaires envoyés | C6: À renseigner après l’événement
A7: Réponses reçues | C7: À renseigner après l’événement
A8: Taux de réponse | B8: =IF(COUNT(B6:B7)<2,"",IFERROR(B7/B6,"")) | C8: Réponses / questionnaires envoyés
A9: Dépenses réelles TTC | C9: À renseigner à partir des dépenses vérifiées
A10: Budget prévisionnel | B10: ='Budget'!D12 | C10: Hypothèses, 2 310 € au départ
A11: Écart réel - prévisionnel | B11: =IF(COUNT(B9)=0,"",B9-B10) | C11: Un écart ne se calcule pas avant saisie des dépenses

Sheet Décisions
A1: Sujet | B1: Décision / preuve | C1: Responsable proposé | D1: Échéance | E1: Statut
A2: Portage et financement | C2: Responsable projet | D2: Avant diffusion | E2: Non confirmé
A3: Date et lieu | C3: Responsable projet / logistique | D3: J-42 | E3: Non confirmé
A4: Intervenants | C4: Éditorial | D4: J-35 | E4: Non confirmé
A5: Assurance et technique | C5: Logistique | D5: J-28 | E5: Non confirmé
A6: Inscriptions et données | C6: Responsable projet / accueil | D6: Avant ouverture | E6: Non ouvert
A7: Dépenses engagées | C7: Responsable projet | D7: Avant commande | E7: Non engagé
